a_jupyterlite_query_config/__init__.py
a_jupyterlite_query_config/_version.py
a_jupyterlite_query_config-0.2.0.data/data/share/jupyter/labextensions/a-jupyterlite-query-config/package.json
a_jupyterlite_query_config-0.2.0.data/data/share/jupyter/labextensions/a-jupyterlite-query-config/static/509.7ef9b3d25303ecedeb75.js
a_jupyterlite_query_config-0.2.0.data/data/share/jupyter/labextensions/a-jupyterlite-query-config/static/728.c6d9af472187a89a25b3.js
a_jupyterlite_query_config-0.2.0.data/data/share/jupyter/labextensions/a-jupyterlite-query-config/static/remoteEntry.2b3fcd71e08ee33f50aa.js
a_jupyterlite_query_config-0.2.0.data/data/share/jupyter/labextensions/a-jupyterlite-query-config/static/style.js
a_jupyterlite_query_config-0.2.0.data/data/share/jupyter/labextensions/a-jupyterlite-query-config/static/third-party-licenses.json
a_jupyterlite_query_config-0.2.0.data/data/share/jupyter/labextensions/a-jupyterlite-query-config/install.json
a_jupyterlite_query_config-0.2.0.dist-info/METADATA
a_jupyterlite_query_config-0.2.0.dist-info/WHEEL
a_jupyterlite_query_config-0.2.0.dist-info/licenses/LICENSE
a_jupyterlite_query_config-0.2.0.dist-info/RECORD
